#######################################################################################################################################
<poster>Dij entertainments</poster>
<fanart>http://s23.postimg.org/e4mt7gr4r/802754_fishing_wallpaper.jpg</fanart>
#######################################################################################################################################

<item>
<title>01 - The Howqua River - Victoria Australia </title>
<link>http://movreel.com/0rgbkhwjy9i8.html</link>
<thumbnail>https://imageshack.com/f/idYQ08ULj</thumbnail>
</item>

<item>
<title>02 - Cotswold Hills - England & Altnaharra - Scotland</title>
<link>http://movreel.com/lwq6heze8oge.html</link>
<thumbnail>https://imageshack.com/f/idYQ08ULj</thumbnail>
</item>

<item>
<title>03 - The D’Urville River - New Zealand</title>
<link>http://movreel.com/0xmyag4p1i72.html</link>
<thumbnail>https://imageshack.com/f/idYQ08ULj</thumbnail>
</item>

<item>
<title>04 - The Chamberlain River - Western Australia</title>
<link>http://movreel.com/afgfbg3ax18c.html</link>
<thumbnail>https://imageshack.com/f/idYQ08ULj</thumbnail>
</item>

<item>
<title>05 - Los Roques - Venezuela</title>
<link>http://movreel.com/2mcecdrmcfud.html</link>
<thumbnail>https://imageshack.com/f/idYQ08ULj</thumbnail>
</item>

<item>
<title>06 - Courmayeur, Valle D’Aosta - Italy</title>
<link>http://movreel.com/uq5s975ekl0k.html</link>
<thumbnail>https://imageshack.com/f/idYQ08ULj</thumbnail>
</item>