#######################################################################################################################################
<poster>Dij entertainments</poster>
<fanart>http://s23.postimg.org/e4mt7gr4r/804754_fishing_wallpaper.jpg</fanart>
#######################################################################################################################################

<item>
<title>Extreme Fishing With Robson Green s04e01</title>
<link>http://movreel.com/k7tsxi0wrm68.html</link>
<thumbnail>http://s17.postimg.org/rj4wj5tdr/download_1.jpg</thumbnail>
</item>

<item>
<title>Extreme Fishing With Robson Green s04e04</title>
<link>http://movreel.com/wrv5epcomend.html</link>
<thumbnail>http://s17.postimg.org/rj4wj5tdr/download_1.jpg</thumbnail>
</item>

<item>
<title>Extreme Fishing With Robson Green s04e04</title>
<link>http://movreel.com/4qwxejryksmj.html</link>
<thumbnail>http://s17.postimg.org/rj4wj5tdr/download_1.jpg</thumbnail>
</item>

<item>
<title>Extreme Fishing With Robson Green s04e04</title>
<link>http://movreel.com/xrtk3n8y3b2n.html</link>
<thumbnail>http://s17.postimg.org/rj4wj5tdr/download_1.jpg</thumbnail>
</item>

<item>
<title>Extreme Fishing With Robson Green s04e05</title>
<link>http://movreel.com/218057nmnooc.html</link>
<thumbnail>http://s17.postimg.org/rj4wj5tdr/download_1.jpg</thumbnail>
</item>

<item>
<title>Extreme Fishing With Robson Green s04e06</title>
<link>http://movreel.com/ekgrkn946hgu.html</link>
<thumbnail>http://s17.postimg.org/rj4wj5tdr/download_1.jpg</thumbnail>
</item>

<item>
<title>Extreme Fishing With Robson Green s04e07</title>
<link>http://movreel.com/ewicy0nm26id.html</link>
<thumbnail>http://s17.postimg.org/rj4wj5tdr/download_1.jpg</thumbnail>
</item>

<item>
<title>Extreme Fishing With Robson Green s04e08</title>
<link>http://movreel.com/nk0zt1wktgr5.html</link>
<thumbnail>http://s17.postimg.org/rj4wj5tdr/download_1.jpg</thumbnail>
</item>

